cellforest/BatchMethodsSC.py
cellforest/CellForest.py
cellforest/PlotMethodsSC.py
cellforest/ProcessMethodsSC.py
cellforest/ProcessSchemaSC.py
cellforest/ReaderMethodsSC.py
cellforest/SpecSC.py
cellforest/WriterMethodsSC.py
cellforest/__init__.py
cellforest/dataprocess_sc.py
cellforest/preprocessing.py
cellforest/config/__init__.py
cellforest/config/default_config.yaml
cellforest/data_structures/Counts.py
cellforest/data_structures/__init__.py
cellforest/hooks/__init__.py
cellforest/hooks/hooks/__init__.py
cellforest/hooks/hooks/matrix_node/__init__.py
cellforest/hooks/hooks/matrix_node/hooks.py
cellforest/hooks/hooks/metadata/__init__.py
cellforest/hooks/hooks/metadata/hooks.py
cellforest/hooks/hooks/unversioned/__init__.py
cellforest/hooks/hooks/unversioned/hooks.py
cellforest/plot/__init__.py
cellforest/plot/root_qc.py
cellforest/processes/__init__.py
cellforest/processes/processes/__init__.py
cellforest/processes/processes/cluster/__init__.py
cellforest/processes/processes/cluster/process.py
cellforest/processes/processes/expression/__init__.py
cellforest/processes/processes/expression/process.py
cellforest/processes/processes/gsea/__init__.py
cellforest/processes/processes/gsea/process.py
cellforest/processes/processes/normalize/__init__.py
cellforest/processes/processes/normalize/process.py
cellforest/processes/processes/reduce/__init__.py
cellforest/processes/processes/reduce/process.py
cellforest/processes/processes/reduce/umap.py
cellforest/processes/processes/test_process/__init__.py
cellforest/processes/processes/test_process/process.py
cellforest/processes/scripts/__init__.py
cellforest/r_utils/__init__.py
cellforest/r_utils/seurat_rds_to_pickle.py
cellforest/r_utils/shell_command.py
cellforest/structures/__init__.py
cellforest/structures/exceptions.py
cellforest/structures/counts/Counts.py
cellforest/structures/counts/CountsStore.py
cellforest/structures/counts/__init__.py
cellforest/structures/counts/build_counts_store.py
cellforest-0.0.1.dist-info/LICENSE
cellforest-0.0.1.dist-info/METADATA
cellforest-0.0.1.dist-info/WHEEL
cellforest-0.0.1.dist-info/top_level.txt
cellforest-0.0.1.dist-info/RECORD
