Metadata-Version: 2.1
Name: cellforest
Version: 0.0.1
Summary: An interactive single-cell bioinformatics workflow manager
Home-page: https://github.com/TheAustinator/cellforest
Author: Austin McKay
Author-email: austinmckay303@gmail.com
License: UNKNOWN
Platform: UNKNOWN
Classifier: Programming Language :: Python :: 3
Classifier: License :: OSI Approved :: GNU Affero General Public License v3 or later (AGPLv3+)
Classifier: Operating System :: OS Independent
Requires-Python: >=3.6
Requires-Dist: matplotlib
Requires-Dist: numba
Requires-Dist: numpy
Requires-Dist: pandas
Requires-Dist: path
Requires-Dist: pathlib
Requires-Dist: pyyaml
Requires-Dist: scipy
Requires-Dist: umap-learn
Provides-Extra: all
Requires-Dist: matplotlib ; extra == 'all'
Requires-Dist: numba ; extra == 'all'
Requires-Dist: numpy ; extra == 'all'
Requires-Dist: pandas ; extra == 'all'
Requires-Dist: path ; extra == 'all'
Requires-Dist: pathlib ; extra == 'all'
Requires-Dist: pyyaml ; extra == 'all'
Requires-Dist: scipy ; extra == 'all'
Requires-Dist: umap-learn ; extra == 'all'
Provides-Extra: dev
Provides-Extra: test
Requires-Dist: pytest ; extra == 'test'
Requires-Dist: requests ; extra == 'test'
